twyleg_kicad_utils/__init__.py
twyleg_kicad_utils/__main__.py
twyleg_kicad_utils/_version.py
twyleg_kicad_utils/build.py
twyleg_kicad_utils/diff.py
twyleg_kicad_utils/main.py
twyleg_kicad_utils/process.py
twyleg_kicad_utils/submodules.py
twyleg_kicad_utils-0.3.2.dist-info/LICENSE
twyleg_kicad_utils-0.3.2.dist-info/METADATA
twyleg_kicad_utils-0.3.2.dist-info/WHEEL
twyleg_kicad_utils-0.3.2.dist-info/entry_points.txt
twyleg_kicad_utils-0.3.2.dist-info/top_level.txt
twyleg_kicad_utils-0.3.2.dist-info/RECORD
