Metadata-Version: 2.1
Name: twyleg-kicad-utils
Version: 0.3.2
Summary: Personal utilities to automate KiCad projects
Home-page: https://github.com/twyleg/twyleg_kicad_utils
Author: Torsten Wylegala
Author-email: mail@twyleg.de
License: GPL 3.0
Keywords: KiCad automation cicd
License-File: LICENSE
